kacs/__init__.py
kacs/generator.py
kacs/git.py
kacs/main.py
kacs/renderer.py
kacs/templates/github.j2
kacs/templates/gitlab.j2
kacs/templates/keepachangelog.j2
kacs/templates/simple.j2
kacs-0.6.0.dist-info/METADATA
kacs-0.6.0.dist-info/WHEEL
kacs-0.6.0.dist-info/entry_points.txt
kacs-0.6.0.dist-info/licenses/LICENSE
kacs-0.6.0.dist-info/RECORD
