Metadata-Version: 2.4
Name: kacs
Version: 0.6.0
Summary: Keep a changelog, stupid! Generate changelogs from git commits using LLM.
Project-URL: Homepage, https://github.com/atasoglu/kacs
Project-URL: Repository, https://github.com/atasoglu/kacs.git
Author-email: Ahmet Atasoglu <ahmetatasoglu98@gmail.com>
License: MIT
License-File: LICENSE
Requires-Python: >=3.9
Requires-Dist: ask2api>=1.1.3
Requires-Dist: jinja2>=3.1.0
Provides-Extra: dev
Requires-Dist: pre-commit; extra == 'dev'
